solpay_seller/__init__.py
solpay_seller/client.py
solpay_seller/compat.py
solpay_seller/exceptions.py
solpay_seller/models.py
solpay_seller/py.typed
solpay_seller/types.py
solpay_seller/webhooks.py
solpay_seller-1.0.1.dist-info/METADATA
solpay_seller-1.0.1.dist-info/WHEEL
solpay_seller-1.0.1.dist-info/top_level.txt
solpay_seller-1.0.1.dist-info/RECORD
