Metadata-Version: 2.4
Name: solpay-seller
Version: 1.0.1
Summary: Python SDK for SolPay Seller API
Author: SolPay
Project-URL: Homepage, https://solpay.one
Project-URL: Documentation, https://solpay.one/dashboard/integrations
Keywords: solpay,seller-api,webhooks,marketplace
Classifier: Programming Language :: Python :: 3
Classifier: Programming Language :: Python :: 3 :: Only
Classifier: Programming Language :: Python :: 3.9
Classifier: Programming Language :: Python :: 3.10
Classifier: Programming Language :: Python :: 3.11
Classifier: Programming Language :: Python :: 3.12
Classifier: License :: Other/Proprietary License
Classifier: Operating System :: OS Independent
Classifier: Intended Audience :: Developers
Classifier: Topic :: Software Development :: Libraries
Classifier: Typing :: Typed
Requires-Python: >=3.9
Requires-Dist: requests>=2.31.0
Provides-Extra: models
Requires-Dist: pydantic>=2.6.0; extra == "models"
Provides-Extra: docs
Requires-Dist: mkdocs>=1.5.0; extra == "docs"
Requires-Dist: mkdocs-material>=9.5.0; extra == "docs"
Requires-Dist: mkdocstrings[python]>=0.25.0; extra == "docs"
Provides-Extra: dev
Requires-Dist: ruff>=0.6.0; extra == "dev"
Requires-Dist: mypy>=1.10.0; extra == "dev"
Requires-Dist: pytest>=8.0.0; extra == "dev"
Requires-Dist: build>=1.2.0; extra == "dev"
Requires-Dist: twine>=5.0.0; extra == "dev"
